AUTHORS
INSTALL
LICENSE
MANIFEST.in
NOTICE
README
requirements.txt
setup.cfg
setup.py
docs/Makefile
docs/conf.py
docs/configuration.rst
docs/faq.rst
docs/index.rst
docs/installation.rst
docs/introduction.rst
docs/make.bat
docs/usage.rst
src/django_thumbnail_works.egg-info/PKG-INFO
src/django_thumbnail_works.egg-info/SOURCES.txt
src/django_thumbnail_works.egg-info/dependency_links.txt
src/django_thumbnail_works.egg-info/not-zip-safe
src/django_thumbnail_works.egg-info/requires.txt
src/django_thumbnail_works.egg-info/top_level.txt
src/thumbnail_works/__init__.py
src/thumbnail_works/exceptions.py
src/thumbnail_works/fields.py
src/thumbnail_works/images.py
src/thumbnail_works/models.py
src/thumbnail_works/settings.py
src/thumbnail_works/tests.py
src/thumbnail_works/utils.py